multilabel_knn/__init__.py
multilabel_knn/binom_multilabel_graph.py
multilabel_knn/binom_multilabel_knn.py
multilabel_knn/evaluation.py
multilabel_knn/knn.py
multilabel_knn/multilabel_knn.py
multilabel_knn-0.0.5.dist-info/LICENSE
multilabel_knn-0.0.5.dist-info/METADATA
multilabel_knn-0.0.5.dist-info/WHEEL
multilabel_knn-0.0.5.dist-info/top_level.txt
multilabel_knn-0.0.5.dist-info/RECORD
