Metadata-Version: 2.1
Name: multilabel-knn
Version: 0.0.5
Summary: A lightweight toolbox for multilabel classification algorithms based on the k-nearest neighbors
Home-page: https://github.com/skojaku/multilabel_knn
Author: Sadamori Kojaku
License: MIT
Keywords: word embedding,graph embedding
Platform: UNKNOWN
Classifier: Development Status :: 3 - Alpha
Classifier: Intended Audience :: Science/Research
Classifier: Topic :: Software Development
Classifier: License :: OSI Approved :: MIT License
Classifier: Programming Language :: Python :: 3.7
Classifier: Programming Language :: Python :: 3.8
License-File: LICENSE
Requires-Dist: faiss-gpu (==1.6.5)
Requires-Dist: scikit-learn
Requires-Dist: numba
Requires-Dist: numpy
Requires-Dist: scipy
